xingAsync/MsgIocpProactor.py
xingAsync/__init__.py
xingAsync/async_api.py
xingAsync/models.py
xingAsync/native.py
xingAsync/resource.py
xingAsync/xing_com.py
xingAsync/res/AS0.res
xingAsync/res/AS1.res
xingAsync/res/AS2.res
xingAsync/res/AS3.res
xingAsync/res/AS4.res
xingAsync/res/B7_.res
xingAsync/res/BMT.res
xingAsync/res/BM_.res
xingAsync/res/C01.res
xingAsync/res/CD0.res
xingAsync/res/CDPCQ04700.res
xingAsync/res/CEXAQ21100.res
xingAsync/res/CEXAQ21200.res
xingAsync/res/CEXAQ31100.res
xingAsync/res/CEXAQ31200.res
xingAsync/res/CEXAQ44200.res
xingAsync/res/CEXAT11100.res
xingAsync/res/CEXAT11200.res
xingAsync/res/CEXAT11300.res
xingAsync/res/CFOAQ00600.res
xingAsync/res/CFOAQ10100.res
xingAsync/res/CFOAQ50600.res
xingAsync/res/CFOAT00100.res
xingAsync/res/CFOAT00200.res
xingAsync/res/CFOAT00300.res
xingAsync/res/CFOBQ10500.res
xingAsync/res/CFOBQ10800.res
xingAsync/res/CFOEQ11100.res
xingAsync/res/CFOEQ82600.res
xingAsync/res/CFOFQ02400.res
xingAsync/res/CIDBQ01400.res
xingAsync/res/CIDBQ01500.res
xingAsync/res/CIDBQ01800.res
xingAsync/res/CIDBQ02400.res
xingAsync/res/CIDBQ03000.res
xingAsync/res/CIDBQ05300.res
xingAsync/res/CIDBT00100.res
xingAsync/res/CIDBT00900.res
xingAsync/res/CIDBT01000.res
xingAsync/res/CIDEQ00800.res
xingAsync/res/CLNAQ00100.res
xingAsync/res/COSAQ00102.res
xingAsync/res/COSAQ01400.res
xingAsync/res/COSAT00301.res
xingAsync/res/COSAT00311.res
xingAsync/res/COSAT00400.res
xingAsync/res/COSMT00300.res
xingAsync/res/COSOQ00201.res
xingAsync/res/COSOQ02701.res
xingAsync/res/CSPAQ00600.res
xingAsync/res/CSPAQ12200.res
xingAsync/res/CSPAQ12300.res
xingAsync/res/CSPAQ13700.res
xingAsync/res/CSPAQ22200.res
xingAsync/res/CSPAT00600.res
xingAsync/res/CSPAT00700.res
xingAsync/res/CSPAT00800.res
xingAsync/res/CSPBQ00200.res
xingAsync/res/CUR.res
xingAsync/res/ChartExcel.res
xingAsync/res/ChartIndex.res
xingAsync/res/DH1.res
xingAsync/res/DHA.res
xingAsync/res/DK3.res
xingAsync/res/DS3.res
xingAsync/res/DVI.res
xingAsync/res/EC0.res
xingasync-0.3.1.dist-info/METADATA
xingasync-0.3.1.dist-info/WHEEL
xingasync-0.3.1.dist-info/licenses/LICENSE
xingasync-0.3.1.dist-info/RECORD
