Metadata-Version: 2.3
Name: xingAsync
Version: 0.3.1
Summary: package for XingApi(DLL,COM)
Project-URL: Homepage, https://github.com/teranum/ls-dev/tree/master/xingAsync
Author-email: teranum <teranum@gmail.com>
Keywords: xingapi
Classifier: License :: OSI Approved :: MIT License
Classifier: Operating System :: OS Independent
Classifier: Programming Language :: Python :: 3
Requires-Python: >=3.8
Requires-Dist: pywin32
